{
  "username": "roberto-perez-cubero",
  "name": "Roberto Perez Cubero",
  "image_url": "https://secure.gravatar.com/avatar/34fb2399c9492ec66cf6d053f1bf0abb?s=96&d=mm&r=g",
  "bio": "Roberto is a Full Stack Engineer on the OpenTok Client SDK team. He loves learning new bits of Android, iOS, Linux, Windows, you name it! In his free time, he is very passionate about programming languages, computer graphics, and video game development for current and old platforms like ZX Spectrum and Commodore 64.",
  "website_url": ""
}